bcl-3.0.0.data/purelib/bcl/__init__.py
bcl-3.0.0.data/purelib/bcl/_sodium.py
bcl-3.0.0.data/purelib/bcl/_sodium.tmpl
bcl-3.0.0.data/purelib/bcl/_sodium_build.py
bcl-3.0.0.data/purelib/bcl/bcl.py
bcl-3.0.0.dist-info/licenses/LICENSE
bcl-3.0.0.dist-info/METADATA
bcl-3.0.0.dist-info/WHEEL
bcl-3.0.0.dist-info/top_level.txt
bcl-3.0.0.dist-info/RECORD
