Metadata-Version: 2.4
Name: bcl
Version: 3.0.0
Summary: Python library that provides a simple interface for symmetric (i.e., secret-key) and asymmetric (i.e., public-key) encryption/decryption primitives.
Home-page: https://github.com/nthparty/bcl
Author: Nth Party
Author-email: team@nthparty.com
License: MIT
Requires-Python: >=3.9
License-File: LICENSE
Provides-Extra: build
Requires-Dist: setuptools>=77.0; extra == "build"
Requires-Dist: wheel~=0.45; extra == "build"
Requires-Dist: pystache~=0.6; extra == "build"
Requires-Dist: build~=1.3; extra == "build"
Provides-Extra: docs
Requires-Dist: sphinx~=7.4; extra == "docs"
Requires-Dist: sphinx-rtd-theme~=3.0; extra == "docs"
Provides-Extra: test
Requires-Dist: pytest~=8.2; extra == "test"
Requires-Dist: pytest-cov~=5.0; extra == "test"
Provides-Extra: lint
Requires-Dist: pylint~=3.3.0; extra == "lint"
Provides-Extra: coveralls
Requires-Dist: coveralls~=4.0; extra == "coveralls"
Provides-Extra: publish
Requires-Dist: build~=1.3; extra == "publish"
Requires-Dist: twine~=4.0; extra == "publish"
Dynamic: license-file
